urlprobe/__init__.py
urlprobe/__main__.py
urlprobe/app.py
urlprobe/cli.py
urlprobe/utils.py
urlprobe-0.1.0.dist-info/METADATA
urlprobe-0.1.0.dist-info/WHEEL
urlprobe-0.1.0.dist-info/entry_points.txt
urlprobe-0.1.0.dist-info/licenses/LICENSE
urlprobe-0.1.0.dist-info/RECORD
