Metadata-Version: 2.4
Name: urlprobe
Version: 0.1.0
Summary: A tool to request a specified `url` and return the response.
License-File: LICENSE
Author: Andrew Vella
Requires-Python: >=3.10,<4.0
Classifier: Programming Language :: Python :: 3
Classifier: Programming Language :: Python :: 3.10
Classifier: Programming Language :: Python :: 3.11
Classifier: Programming Language :: Python :: 3.12
Classifier: Programming Language :: Python :: 3.13
Classifier: Programming Language :: Python :: 3.14
Requires-Dist: click (>=8.2.1,<9.0.0)
Requires-Dist: flask (>=3.0.0,<4.0.0)
Requires-Dist: requests (>=2.32.3,<3.0.0)
Requires-Dist: rich (>=14.0.0,<15.0.0)
Requires-Dist: toml (>=0.10.2,<0.11.0)
